{
    "format-version": 0,
    "time": 1742269089,
    "files": [
        {
            "load_address": 49664,
            "version_MCUBOOT": "0.0.0+0",
            "type": "application",
            "board": "microminutes_v1_1",
            "soc": "nRF52833_QDAA",
            "size": 165852,
            "file": "app_update.bin",
            "modtime": 1742269089
        }
    ],
    "name": "DEV_KIT_MicroMinutes",
    "firmware": {
        "zephyr": {
            "revision": "fa4a8baff2177b9a9d63e95b270b3cf85c8e66a3-dirty"
        },
        "nrf": {
            "revision": "eef645c4a31201df353fdff5447262d7675fa1c1-dirty"
        }
    }
}